set_env/__init__.py
set_env/set_env.py
set_env_colab_kaggle_dotenv-0.1.3.dist-info/METADATA
set_env_colab_kaggle_dotenv-0.1.3.dist-info/WHEEL
set_env_colab_kaggle_dotenv-0.1.3.dist-info/entry_points.txt
set_env_colab_kaggle_dotenv-0.1.3.dist-info/RECORD
