Metadata-Version: 2.3
Name: set-env-colab-kaggle-dotenv
Version: 0.1.3
Summary: Set an environ variable in colab/kaggle/dotenv(.env/dotenv/env)
Author: ffreemt
Requires-Python: >=3.8
Requires-Dist: loguru>=0.7.2
Requires-Dist: python-dotenv>=1.0.0
